dirtools2.py
dirtools2/__init__.py
dirtools2/__main__.py
dirtools2/dirtools2.py
dirtools2/test_dirtools.py
dirtools2-0.2.16.dist-info/LICENSE
dirtools2-0.2.16.dist-info/METADATA
dirtools2-0.2.16.dist-info/WHEEL
dirtools2-0.2.16.dist-info/top_level.txt
dirtools2-0.2.16.dist-info/RECORD
